datadiligence/__init__.py
datadiligence/bootstrap.py
datadiligence/exceptions.py
datadiligence/utils.py
datadiligence/evaluators/__init__.py
datadiligence/evaluators/base.py
datadiligence/evaluators/file_evaluator.py
datadiligence/evaluators/http.py
datadiligence/evaluators/postprocess.py
datadiligence/evaluators/preprocess.py
datadiligence/rules/__init__.py
datadiligence/rules/_c2pa.py
datadiligence/rules/base.py
datadiligence/rules/http.py
datadiligence/rules/spawning.py
datadiligence-0.1.7.dist-info/LICENSE.txt
datadiligence-0.1.7.dist-info/METADATA
datadiligence-0.1.7.dist-info/WHEEL
datadiligence-0.1.7.dist-info/top_level.txt
datadiligence-0.1.7.dist-info/RECORD
