Metadata-Version: 2.1
Name: datadiligence
Version: 0.1.7
Summary: Respect generative AI opt-outs in your ML and training pipeline.
Home-page: https://github.com/Spawning-Inc/datadiligence/
Author: Nick Padgett
Author-email: nick@spawning.ai
License: MIT
Project-URL: Documentation, https://datadiligence.readthedocs.io/en/latest/quickstart.html
Project-URL: Source, https://github.com/Spawning-Inc/datadiligence/
Project-URL: Changelog, https://datadiligence.readthedocs.io/en/latest/changelog.html
Project-URL: Tracker, https://github.com/Spawning-Inc/datadiligence/issues
Platform: any
Classifier: Development Status :: 4 - Beta
Classifier: Programming Language :: Python
Requires-Python: >=3.7
License-File: LICENSE.txt
Requires-Dist: requests >=2.19.1
Requires-Dist: aiohttp >=3.6.0
Requires-Dist: c2pa-python >=0.1.0
Requires-Dist: cryptography
Requires-Dist: pillow
Requires-Dist: importlib-metadata ; python_version < "3.8"
Provides-Extra: testing
Requires-Dist: setuptools ; extra == 'testing'
Requires-Dist: pytest ; extra == 'testing'
Requires-Dist: pytest-cov ; extra == 'testing'
Requires-Dist: flask ; extra == 'testing'
